naeval/__init__.py
naeval/const.py
naeval/dataset.py
naeval/docker.py
naeval/io.py
naeval/log.py
naeval/model.py
naeval/readme.py
naeval/record.py
naeval/report.py
naeval/score.py
naeval/sent.py
naeval/span.py
naeval/tokenizer.py
naeval/emb/__init__.py
naeval/emb/datasets.py
naeval/emb/models.py
naeval/emb/report.py
naeval/emb/score.py
naeval/morph/__init__.py
naeval/morph/datasets.py
naeval/morph/markup.py
naeval/morph/report.py
naeval/morph/score.py
naeval/morph/models/__init__.py
naeval/morph/models/base.py
naeval/morph/models/conll.py
naeval/morph/models/deeppavlov.py
naeval/morph/models/maru.py
naeval/morph/models/rnnmorph.py
naeval/morph/models/rupostagger.py
naeval/morph/models/spacy.py
naeval/morph/models/udpipe.py
naeval/ner/__init__.py
naeval/ner/adapt.py
naeval/ner/bio.py
naeval/ner/markup.py
naeval/ner/report.py
naeval/ner/score.py
naeval/ner/datasets/__init__.py
naeval/ner/datasets/bsnlp.py
naeval/ner/datasets/factru.py
naeval/ner/datasets/gareev.py
naeval/ner/datasets/ne5.py
naeval/ner/datasets/wikiner.py
naeval/ner/models/__init__.py
naeval/ner/models/base.py
naeval/ner/models/deeppavlov.py
naeval/ner/models/mitie.py
naeval/ner/models/natasha.py
naeval/ner/models/pullenti.py
naeval/ner/models/texterra.py
naeval/ner/models/token.py
naeval/ner/models/tomita.py
naeval/segment/__init__.py
naeval/segment/datasets.py
naeval/segment/models.py
naeval/segment/partition.py
naeval/segment/report.py
naeval/segment/score.py
naeval/segment/substring.py
naeval/syntax/__init__.py
naeval/syntax/datasets.py
naeval/syntax/markup.py
naeval/syntax/report.py
naeval/syntax/score.py
naeval/syntax/models/__init__.py
naeval/syntax/models/base.py
naeval/syntax/models/deeppavlov.py
naeval/syntax/models/spacy.py
naeval/syntax/models/udpipe.py
naeval-0.2.0.dist-info/METADATA
naeval-0.2.0.dist-info/WHEEL
naeval-0.2.0.dist-info/top_level.txt
naeval-0.2.0.dist-info/RECORD
