Metadata-Version: 2.1
Name: naeval
Version: 0.2.0
Summary: Comparing quality and performance of NLP systems for Russian language
Home-page: https://github.com/natasha/naeval
Author: Alexander Kukushkin
Author-email: alex@alexkuk.ru
License: MIT
Keywords: nlp,russian,evaluation
Platform: UNKNOWN
Classifier: License :: OSI Approved :: MIT License
Classifier: Programming Language :: Python :: 3
Classifier: Topic :: Scientific/Engineering :: Artificial Intelligence
